ipoly/LaTeX.py
ipoly/__init__.py
ipoly/communication.py
ipoly/file_management.py
ipoly/img/ipoly.ico
ipoly/logger.py
ipoly/ml.py
ipoly/scraping.py
ipoly/traceback.py
ipoly/visualisation.py
ipoly-0.2.1.dist-info/LICENSE
ipoly-0.2.1.dist-info/METADATA
ipoly-0.2.1.dist-info/WHEEL
ipoly-0.2.1.dist-info/RECORD
