Metadata-Version: 2.1
Name: ipoly
Version: 0.2.1
Summary: Data Science utilities.
Home-page: https://github.com/Danguilhen/ipoly
License: MIT
Author: Thomas Danguilhen
Author-email: ipoly.8vqpv@slmails.com
Requires-Python: >=3.10,<3.12
Classifier: License :: OSI Approved :: MIT License
Classifier: Programming Language :: Python :: 3
Classifier: Programming Language :: Python :: 3.10
Classifier: Programming Language :: Python :: 3.11
Provides-Extra: dicom
Provides-Extra: image
Provides-Extra: ml
Provides-Extra: table
Provides-Extra: torch
Requires-Dist: IPython (>=8.11)
Requires-Dist: albumentations (>=1.3) ; extra == "image"
Requires-Dist: beautifulsoup4 (>=4.10,<5.0)
Requires-Dist: colorama (>=0.4,<0.5)
Requires-Dist: glob2 (>=0.7,<0.8)
Requires-Dist: lazypredict (>=0.2) ; extra == "ml"
Requires-Dist: nptyping (>=1.4,<2.0)
Requires-Dist: numpy (<1.24)
Requires-Dist: nvsmi (>=0.4) ; extra == "ml"
Requires-Dist: opencv-python (>=4.7) ; extra == "image"
Requires-Dist: openpyxl (>=3.1) ; extra == "table"
Requires-Dist: pandas (>=2.0)
Requires-Dist: plyer (>=2.0,<3.0)
Requires-Dist: polars (>=0.18.0) ; extra == "table"
Requires-Dist: pyarrow (>=12.0) ; extra == "table"
Requires-Dist: pydicom (>=2.3) ; extra == "dicom"
Requires-Dist: scikit-image (>=0.20.0) ; extra == "image"
Requires-Dist: scipy (>=1.10) ; extra == "ml"
Requires-Dist: seaborn (>=0.12) ; extra == "ml"
Requires-Dist: selenium (>=4.6,<5.0)
Requires-Dist: tensorflow (>=2.7,<3.0)
Requires-Dist: tensorflow-io-gcs-filesystem (==0.31.0)
Requires-Dist: torch (>=2.0) ; extra == "torch"
Requires-Dist: transformers (>=4.0) ; extra == "ml"
Requires-Dist: typeguard (>=3.0.2)
Requires-Dist: ultralytics (>=8.0) ; extra == "image"
Requires-Dist: webdriver-manager (>=3.5,<4.0)
Requires-Dist: xlrd (>=2.0) ; extra == "table"
Project-URL: Documentation, https://ipoly.readthedocs.io/en/latest/source/ipoly.html
Project-URL: Repository, https://github.com/Danguilhen/ipoly
